{"cameraMode":{"drawMode":0,"name":"Shaded","section":"Shading Mode"},"sceneLighting":true,"audioPlay":false,"sceneViewState":{"showFog":true,"showMaterialUpdate":false,"showSkybox":true,"showFlares":true,"showImageEffects":true,"showParticleSystems":true},"in2DMode":false,"pivot":{"x":0.06612920016050339,"y":4.29810094833374,"z":-23.579574584960939},"rotation":{"x":-0.28261035680770876,"y":-0.004607272334396839,"z":0.001357055502012372,"w":-0.9592462778091431},"size":33.10549545288086,"orthographic":false}